f99_erp_api_pb2.py
f99_erp_api_pb2_grpc.py
f99_erp_api-1.0.3.dist-info/METADATA
f99_erp_api-1.0.3.dist-info/WHEEL
f99_erp_api-1.0.3.dist-info/top_level.txt
f99_erp_api-1.0.3.dist-info/RECORD
