Metadata-Version: 2.1
Name: f99-erp-api
Version: 1.0.3
Summary: F99 Erp API
Home-page: UNKNOWN
Author: DTQ
License: UNKNOWN
Platform: UNKNOWN
Classifier: Programming Language :: Python :: 3
Classifier: License :: OSI Approved :: MIT License
Classifier: Operating System :: OS Independent
Requires-Python: >=3.6
Requires-Dist: grpcio (==1.26.0)
Requires-Dist: grpcio-tools (==1.26.0)
